generate_testcase
setup.py
Appium_UIAutomation.egg-info/PKG-INFO
Appium_UIAutomation.egg-info/SOURCES.txt
Appium_UIAutomation.egg-info/dependency_links.txt
Appium_UIAutomation.egg-info/requires.txt
Appium_UIAutomation.egg-info/top_level.txt
automation/__init__.py
automation/template_desired_capabilities.txt
automation/template_testcase.txt
automation/mobile/__init__.py
automation/mobile/mobdriver.py
automation/mobile/platforms.py
automation/mobile/uicomponents.py